sjtuautorun/__init__.py
sjtuautorun/constants/__init__.py
sjtuautorun/constants/custom_exceptions.py
sjtuautorun/constants/data_roots.py
sjtuautorun/constants/global_attribute.py
sjtuautorun/constants/image_templates.py
sjtuautorun/controller/__init__.py
sjtuautorun/controller/android_controller.py
sjtuautorun/controller/emulator.py
sjtuautorun/controller/run_timer.py
sjtuautorun/controller/windows_controller.py
sjtuautorun/data/default_settings.yaml
sjtuautorun/data/images/confirm_image/1.png
sjtuautorun/data/images/confirm_image/2.png
sjtuautorun/data/images/confirm_image/3.png
sjtuautorun/data/images/confirm_image/4.png
sjtuautorun/data/images/confirm_image/5.png
sjtuautorun/data/images/confirm_image/6.png
sjtuautorun/data/images/run_image/1.png
sjtuautorun/data/images/run_image/2.png
sjtuautorun/data/images/run_image/3.png
sjtuautorun/data/images/run_image/4.png
sjtuautorun/data/images/setting_image/1.png
sjtuautorun/data/images/setting_image/2.png
sjtuautorun/data/images/setting_image/3.png
sjtuautorun/data/images/setting_image/4.png
sjtuautorun/data/images/start_image/1.png
sjtuautorun/data/images/start_image/2.png
sjtuautorun/data/images/start_image/3.png
sjtuautorun/data/images/update_image/1.png
sjtuautorun/data/plans/default.yaml
sjtuautorun/data/plans/光体.yaml
sjtuautorun/data/plans/召唤阵.yaml
sjtuautorun/data/plans/宣怀大道.yaml
sjtuautorun/mygo/__init__.py
sjtuautorun/mygo/run_plan.py
sjtuautorun/scripts/__init__.py
sjtuautorun/scripts/main.py
sjtuautorun/utils/__init__.py
sjtuautorun/utils/api_image.py
sjtuautorun/utils/function_wrapper.py
sjtuautorun/utils/io.py
sjtuautorun/utils/math_functions.py
sjtuautorun/utils/new_logger.py
sjtuautorun/utils/update.py
sjtuautorun-0.3.2.1.dist-info/LICENSE
sjtuautorun-0.3.2.1.dist-info/METADATA
sjtuautorun-0.3.2.1.dist-info/WHEEL
sjtuautorun-0.3.2.1.dist-info/RECORD
