Metadata-Version: 2.1
Name: sjtuautorun
Version: 0.3.2.1
Summary: 交我润
License: MIT
Author: cwlm_ma
Requires-Python: >=3.11,<3.12
Classifier: License :: OSI Approved :: MIT License
Classifier: Programming Language :: Python :: 3
Classifier: Programming Language :: Python :: 3.11
Requires-Dist: airtest (>=1.3.1,<2.0.0)
Requires-Dist: easyocr (>=1.7.1,<2.0.0)
Requires-Dist: geopy (>=2.4.1,<3.0.0)
Requires-Dist: inquirer (>=3.2.4,<4.0.0)
Requires-Dist: numpy (==1.26.4)
Requires-Dist: opencv-python (==4.10.0.84)
